README.rst
setup.py
fbetl/__init__.py
fbetl.egg-info/PKG-INFO
fbetl.egg-info/SOURCES.txt
fbetl.egg-info/dependency_links.txt
fbetl.egg-info/top_level.txt
fbetl/extractors/__init__.py
fbetl/extractors/comments.py
fbetl/extractors/extractor.py
fbetl/extractors/messages.py
fbetl/extractors/posts.py
fbetl/extractors/reactions.py
tests/__init__.py
tests/test.py