Metadata-Version: 1.1
Name: fbetl
Version: 0.1.2
Summary: UNKNOWN
Home-page: https://github.com/gregology/fbetl
Author: Greg Clarke
Author-email: greg@gho.st
License: MIT
Keywords: facebook,data
Platform: UNKNOWN
Classifier: Development Status :: 4 - Beta
Classifier: Intended Audience :: Developers
Classifier: Topic :: Software Development :: Build Tools
Classifier: License :: OSI Approved :: MIT License
Classifier: Programming Language :: Python
